README.md
setup.py
TOPSIS_ADHIVIR_101866009/__init__.py
TOPSIS_ADHIVIR_101866009/adhivir.py
TOPSIS_ADHIVIR_101866009.egg-info/PKG-INFO
TOPSIS_ADHIVIR_101866009.egg-info/SOURCES.txt
TOPSIS_ADHIVIR_101866009.egg-info/dependency_links.txt
TOPSIS_ADHIVIR_101866009.egg-info/requires.txt
TOPSIS_ADHIVIR_101866009.egg-info/top_level.txt