Metadata-Version: 1.1
Name: TOPSIS-ADHIVIR-101866009
Version: 0.1
Summary: TOPSIS implementation
Home-page: UNKNOWN
Author: ADHIVIR SINGH RANA
Author-email: arana60_be18@thapar.edu
License: MIT
Keywords: TOSPSIS,Normalised_Matrix,Performance_score,Rank,Weighted_Normalised_matrix,TOPSIS SCORE
Platform: UNKNOWN
Classifier: Development Status :: 3 - Alpha
Classifier: Intended Audience :: Developers
Classifier: Topic :: Software Development :: Build Tools
Classifier: License :: OSI Approved :: MIT License
Classifier: Programming Language :: Python :: 3
Classifier: Programming Language :: Python :: 3.4
Classifier: Programming Language :: Python :: 3.5
Classifier: Programming Language :: Python :: 3.6
Classifier: License :: OSI Approved :: MIT License
